pokemon_yeet/__init__.py
pokemon_yeet-0.0.0.dist-info/WHEEL
pokemon_yeet-0.0.0.dist-info/METADATA
pokemon_yeet-0.0.0.dist-info/RECORD
