Metadata-Version: 2.1
Name: pokemon_yeet
Version: 0.0.0
Summary: This is an auto battling pokemon cli game
Home-page: https://github/mastermndio/pokemon_yeet
License: UNKNOWN
Author: Aaron Brooks
Author-email: abrooks@mastermnd.io
